indexedsearch/__init__.py
indexedsearch/config_spec.ini
indexedsearch/forms.py
indexedsearch/views.py
indexedsearch/backends/__init__.py
indexedsearch/backends/whoosh.py
indexedsearch/templates/indexedsearch/base_search_link.html
indexedsearch/templates/indexedsearch/results.html
indexedsearch/templates/indexedsearch/search_link_button.html
indexedsearch/templates/indexedsearch/search_link_form.html
indexedsearch/templates/indexedsearch/search_link_link.html
indexedsearch/templates/indexedsearch/search_link_none.html
mediagoblin_indexedsearch-0.1.1.dist-info/DESCRIPTION.rst
mediagoblin_indexedsearch-0.1.1.dist-info/METADATA
mediagoblin_indexedsearch-0.1.1.dist-info/RECORD
mediagoblin_indexedsearch-0.1.1.dist-info/WHEEL
mediagoblin_indexedsearch-0.1.1.dist-info/metadata.json
mediagoblin_indexedsearch-0.1.1.dist-info/top_level.txt
test/__init__.py
test/conftest.py
test/test_search_form.py
test/test_search_link.py
test/test_whoosh_engine.py
