Metadata-Version: 2.0
Name: mediagoblin-indexedsearch
Version: 0.1.1
Summary: A search plugin for GNU mediagoblin.
Home-page: https://github.com/tofay/mediagoblin-indexedsearch
Author: Tom Fay
Author-email: tom@teamfay.co.uk
License: AGPLv3
Platform: UNKNOWN
Classifier: Development Status :: 3 - Alpha
Classifier: License :: OSI Approved :: GNU Affero General Public License v3
Classifier: Programming Language :: Python :: 2
Classifier: Programming Language :: Python :: 2.7
Classifier: Programming Language :: Python :: 3
Classifier: Programming Language :: Python :: 3.4
Classifier: Programming Language :: Python :: 3.5
Requires-Dist: whoosh
